{
  "version": "5",
  "dialect": "mysql",
  "id": "f4678ccb-7b99-4bcb-9967-62a1a6e75e87",
  "prevId": "e557f44d-07eb-4e3c-8fd0-e69319679904",
  "tables": {
    "applications": {
      "name": "applications",
      "columns": {
        "id": {
          "name": "id",
          "type": "int",
          "primaryKey": false,
          "notNull": true,
          "autoincrement": true
        },
        "userId": {
          "name": "userId",
          "type": "int",
          "primaryKey": false,
          "notNull": true,
          "autoincrement": false
        },
        "companyName": {
          "name": "companyName",
          "type": "varchar(255)",
          "primaryKey": false,
          "notNull": true,
          "autoincrement": false
        },
        "industry": {
          "name": "industry",
          "type": "varchar(128)",
          "primaryKey": false,
          "notNull": false,
          "autoincrement": false
        },
        "description": {
          "name": "description",
          "type": "text",
          "primaryKey": false,
          "notNull": false,
          "autoincrement": false
        },
        "descriptionI18n": {
          "name": "descriptionI18n",
          "type": "json",
          "primaryKey": false,
          "notNull": false,
          "autoincrement": false
        },
        "status": {
          "name": "status",
          "type": "enum('pending','reviewing','approved','rejected')",
          "primaryKey": false,
          "notNull": true,
          "autoincrement": false,
          "default": "'pending'"
        },
        "certificationLevel": {
          "name": "certificationLevel",
          "type": "enum('L1','L2','L3')",
          "primaryKey": false,
          "notNull": true,
          "autoincrement": false,
          "default": "'L1'"
        },
        "adminNotes": {
          "name": "adminNotes",
          "type": "text",
          "primaryKey": false,
          "notNull": false,
          "autoincrement": false
        },
        "createdAt": {
          "name": "createdAt",
          "type": "timestamp",
          "primaryKey": false,
          "notNull": true,
          "autoincrement": false,
          "default": "(now())"
        },
        "updatedAt": {
          "name": "updatedAt",
          "type": "timestamp",
          "primaryKey": false,
          "notNull": true,
          "autoincrement": false,
          "onUpdate": true,
          "default": "(now())"
        }
      },
      "indexes": {},
      "foreignKeys": {},
      "compositePrimaryKeys": {
        "applications_id": {
          "name": "applications_id",
          "columns": [
            "id"
          ]
        }
      },
      "uniqueConstraints": {},
      "checkConstraint": {}
    },
    "certificates": {
      "name": "certificates",
      "columns": {
        "id": {
          "name": "id",
          "type": "int",
          "primaryKey": false,
          "notNull": true,
          "autoincrement": true
        },
        "userId": {
          "name": "userId",
          "type": "int",
          "primaryKey": false,
          "notNull": true,
          "autoincrement": false
        },
        "projectId": {
          "name": "projectId",
          "type": "int",
          "primaryKey": false,
          "notNull": false,
          "autoincrement": false
        },
        "certificateNumber": {
          "name": "certificateNumber",
          "type": "varchar(64)",
          "primaryKey": false,
          "notNull": true,
          "autoincrement": false
        },
        "level": {
          "name": "level",
          "type": "enum('L1','L2','L3')",
          "primaryKey": false,
          "notNull": true,
          "autoincrement": false
        },
        "title": {
          "name": "title",
          "type": "varchar(255)",
          "primaryKey": false,
          "notNull": true,
          "autoincrement": false
        },
        "titleI18n": {
          "name": "titleI18n",
          "type": "json",
          "primaryKey": false,
          "notNull": false,
          "autoincrement": false
        },
        "holderName": {
          "name": "holderName",
          "type": "varchar(255)",
          "primaryKey": false,
          "notNull": true,
          "autoincrement": false
        },
        "issuedAt": {
          "name": "issuedAt",
          "type": "timestamp",
          "primaryKey": false,
          "notNull": true,
          "autoincrement": false,
          "default": "(now())"
        },
        "expiresAt": {
          "name": "expiresAt",
          "type": "timestamp",
          "primaryKey": false,
          "notNull": false,
          "autoincrement": false
        },
        "status": {
          "name": "status",
          "type": "enum('active','expired','revoked')",
          "primaryKey": false,
          "notNull": true,
          "autoincrement": false,
          "default": "'active'"
        },
        "createdAt": {
          "name": "createdAt",
          "type": "timestamp",
          "primaryKey": false,
          "notNull": true,
          "autoincrement": false,
          "default": "(now())"
        },
        "updatedAt": {
          "name": "updatedAt",
          "type": "timestamp",
          "primaryKey": false,
          "notNull": true,
          "autoincrement": false,
          "onUpdate": true,
          "default": "(now())"
        }
      },
      "indexes": {},
      "foreignKeys": {},
      "compositePrimaryKeys": {
        "certificates_id": {
          "name": "certificates_id",
          "columns": [
            "id"
          ]
        }
      },
      "uniqueConstraints": {
        "certificates_certificateNumber_unique": {
          "name": "certificates_certificateNumber_unique",
          "columns": [
            "certificateNumber"
          ]
        }
      },
      "checkConstraint": {}
    },
    "courses": {
      "name": "courses",
      "columns": {
        "id": {
          "name": "id",
          "type": "int",
          "primaryKey": false,
          "notNull": true,
          "autoincrement": true
        },
        "slug": {
          "name": "slug",
          "type": "varchar(64)",
          "primaryKey": false,
          "notNull": true,
          "autoincrement": false
        },
        "nameEn": {
          "name": "nameEn",
          "type": "varchar(255)",
          "primaryKey": false,
          "notNull": true,
          "autoincrement": false
        },
        "nameZh": {
          "name": "nameZh",
          "type": "varchar(255)",
          "primaryKey": false,
          "notNull": false,
          "autoincrement": false
        },
        "nameFr": {
          "name": "nameFr",
          "type": "varchar(255)",
          "primaryKey": false,
          "notNull": false,
          "autoincrement": false
        },
        "nameJa": {
          "name": "nameJa",
          "type": "varchar(255)",
          "primaryKey": false,
          "notNull": false,
          "autoincrement": false
        },
        "taglineEn": {
          "name": "taglineEn",
          "type": "varchar(512)",
          "primaryKey": false,
          "notNull": false,
          "autoincrement": false
        },
        "taglineZh": {
          "name": "taglineZh",
          "type": "varchar(512)",
          "primaryKey": false,
          "notNull": false,
          "autoincrement": false
        },
        "taglineFr": {
          "name": "taglineFr",
          "type": "varchar(512)",
          "primaryKey": false,
          "notNull": false,
          "autoincrement": false
        },
        "taglineJa": {
          "name": "taglineJa",
          "type": "varchar(512)",
          "primaryKey": false,
          "notNull": false,
          "autoincrement": false
        },
        "descriptionEn": {
          "name": "descriptionEn",
          "type": "text",
          "primaryKey": false,
          "notNull": false,
          "autoincrement": false
        },
        "descriptionZh": {
          "name": "descriptionZh",
          "type": "text",
          "primaryKey": false,
          "notNull": false,
          "autoincrement": false
        },
        "descriptionFr": {
          "name": "descriptionFr",
          "type": "text",
          "primaryKey": false,
          "notNull": false,
          "autoincrement": false
        },
        "descriptionJa": {
          "name": "descriptionJa",
          "type": "text",
          "primaryKey": false,
          "notNull": false,
          "autoincrement": false
        },
        "category": {
          "name": "category",
          "type": "varchar(64)",
          "primaryKey": false,
          "notNull": false,
          "autoincrement": false
        },
        "targetAudienceEn": {
          "name": "targetAudienceEn",
          "type": "varchar(512)",
          "primaryKey": false,
          "notNull": false,
          "autoincrement": false
        },
        "targetAudienceZh": {
          "name": "targetAudienceZh",
          "type": "varchar(512)",
          "primaryKey": false,
          "notNull": false,
          "autoincrement": false
        },
        "duration": {
          "name": "duration",
          "type": "varchar(64)",
          "primaryKey": false,
          "notNull": false,
          "autoincrement": false
        },
        "priceInfo": {
          "name": "priceInfo",
          "type": "varchar(128)",
          "primaryKey": false,
          "notNull": false,
          "autoincrement": false
        },
        "coverImageUrl": {
          "name": "coverImageUrl",
          "type": "varchar(512)",
          "primaryKey": false,
          "notNull": false,
          "autoincrement": false
        },
        "icon": {
          "name": "icon",
          "type": "varchar(16)",
          "primaryKey": false,
          "notNull": false,
          "autoincrement": false
        },
        "themeColor": {
          "name": "themeColor",
          "type": "varchar(16)",
          "primaryKey": false,
          "notNull": false,
          "autoincrement": false
        },
        "highlights": {
          "name": "highlights",
          "type": "json",
          "primaryKey": false,
          "notNull": false,
          "autoincrement": false
        },
        "isVisible": {
          "name": "isVisible",
          "type": "enum('visible','hidden')",
          "primaryKey": false,
          "notNull": true,
          "autoincrement": false,
          "default": "'visible'"
        },
        "displayOrder": {
          "name": "displayOrder",
          "type": "int",
          "primaryKey": false,
          "notNull": true,
          "autoincrement": false,
          "default": 0
        },
        "createdAt": {
          "name": "createdAt",
          "type": "timestamp",
          "primaryKey": false,
          "notNull": true,
          "autoincrement": false,
          "default": "(now())"
        },
        "updatedAt": {
          "name": "updatedAt",
          "type": "timestamp",
          "primaryKey": false,
          "notNull": true,
          "autoincrement": false,
          "onUpdate": true,
          "default": "(now())"
        }
      },
      "indexes": {},
      "foreignKeys": {},
      "compositePrimaryKeys": {
        "courses_id": {
          "name": "courses_id",
          "columns": [
            "id"
          ]
        }
      },
      "uniqueConstraints": {
        "courses_slug_unique": {
          "name": "courses_slug_unique",
          "columns": [
            "slug"
          ]
        }
      },
      "checkConstraint": {}
    },
    "experts": {
      "name": "experts",
      "columns": {
        "id": {
          "name": "id",
          "type": "int",
          "primaryKey": false,
          "notNull": true,
          "autoincrement": true
        },
        "nameEn": {
          "name": "nameEn",
          "type": "varchar(128)",
          "primaryKey": false,
          "notNull": true,
          "autoincrement": false
        },
        "nameZh": {
          "name": "nameZh",
          "type": "varchar(128)",
          "primaryKey": false,
          "notNull": false,
          "autoincrement": false
        },
        "nameFr": {
          "name": "nameFr",
          "type": "varchar(128)",
          "primaryKey": false,
          "notNull": false,
          "autoincrement": false
        },
        "nameJa": {
          "name": "nameJa",
          "type": "varchar(128)",
          "primaryKey": false,
          "notNull": false,
          "autoincrement": false
        },
        "roleEn": {
          "name": "roleEn",
          "type": "varchar(128)",
          "primaryKey": false,
          "notNull": false,
          "autoincrement": false
        },
        "roleZh": {
          "name": "roleZh",
          "type": "varchar(128)",
          "primaryKey": false,
          "notNull": false,
          "autoincrement": false
        },
        "roleFr": {
          "name": "roleFr",
          "type": "varchar(128)",
          "primaryKey": false,
          "notNull": false,
          "autoincrement": false
        },
        "roleJa": {
          "name": "roleJa",
          "type": "varchar(128)",
          "primaryKey": false,
          "notNull": false,
          "autoincrement": false
        },
        "titleEn": {
          "name": "titleEn",
          "type": "varchar(255)",
          "primaryKey": false,
          "notNull": false,
          "autoincrement": false
        },
        "titleZh": {
          "name": "titleZh",
          "type": "varchar(255)",
          "primaryKey": false,
          "notNull": false,
          "autoincrement": false
        },
        "titleFr": {
          "name": "titleFr",
          "type": "varchar(255)",
          "primaryKey": false,
          "notNull": false,
          "autoincrement": false
        },
        "titleJa": {
          "name": "titleJa",
          "type": "varchar(255)",
          "primaryKey": false,
          "notNull": false,
          "autoincrement": false
        },
        "bioEn": {
          "name": "bioEn",
          "type": "text",
          "primaryKey": false,
          "notNull": false,
          "autoincrement": false
        },
        "bioZh": {
          "name": "bioZh",
          "type": "text",
          "primaryKey": false,
          "notNull": false,
          "autoincrement": false
        },
        "bioFr": {
          "name": "bioFr",
          "type": "text",
          "primaryKey": false,
          "notNull": false,
          "autoincrement": false
        },
        "bioJa": {
          "name": "bioJa",
          "type": "text",
          "primaryKey": false,
          "notNull": false,
          "autoincrement": false
        },
        "avatarUrl": {
          "name": "avatarUrl",
          "type": "varchar(512)",
          "primaryKey": false,
          "notNull": false,
          "autoincrement": false
        },
        "sortOrder": {
          "name": "sortOrder",
          "type": "int",
          "primaryKey": false,
          "notNull": true,
          "autoincrement": false,
          "default": 0
        },
        "isVisible": {
          "name": "isVisible",
          "type": "enum('visible','hidden')",
          "primaryKey": false,
          "notNull": true,
          "autoincrement": false,
          "default": "'visible'"
        },
        "displayOrder": {
          "name": "displayOrder",
          "type": "int",
          "primaryKey": false,
          "notNull": true,
          "autoincrement": false,
          "default": 0
        },
        "createdAt": {
          "name": "createdAt",
          "type": "timestamp",
          "primaryKey": false,
          "notNull": true,
          "autoincrement": false,
          "default": "(now())"
        },
        "updatedAt": {
          "name": "updatedAt",
          "type": "timestamp",
          "primaryKey": false,
          "notNull": true,
          "autoincrement": false,
          "onUpdate": true,
          "default": "(now())"
        }
      },
      "indexes": {},
      "foreignKeys": {},
      "compositePrimaryKeys": {
        "experts_id": {
          "name": "experts_id",
          "columns": [
            "id"
          ]
        }
      },
      "uniqueConstraints": {},
      "checkConstraint": {}
    },
    "methodologies": {
      "name": "methodologies",
      "columns": {
        "id": {
          "name": "id",
          "type": "int",
          "primaryKey": false,
          "notNull": true,
          "autoincrement": true
        },
        "slug": {
          "name": "slug",
          "type": "varchar(64)",
          "primaryKey": false,
          "notNull": true,
          "autoincrement": false
        },
        "nameEn": {
          "name": "nameEn",
          "type": "varchar(255)",
          "primaryKey": false,
          "notNull": true,
          "autoincrement": false
        },
        "nameZh": {
          "name": "nameZh",
          "type": "varchar(255)",
          "primaryKey": false,
          "notNull": false,
          "autoincrement": false
        },
        "nameFr": {
          "name": "nameFr",
          "type": "varchar(255)",
          "primaryKey": false,
          "notNull": false,
          "autoincrement": false
        },
        "nameJa": {
          "name": "nameJa",
          "type": "varchar(255)",
          "primaryKey": false,
          "notNull": false,
          "autoincrement": false
        },
        "taglineEn": {
          "name": "taglineEn",
          "type": "varchar(512)",
          "primaryKey": false,
          "notNull": false,
          "autoincrement": false
        },
        "taglineZh": {
          "name": "taglineZh",
          "type": "varchar(512)",
          "primaryKey": false,
          "notNull": false,
          "autoincrement": false
        },
        "taglineFr": {
          "name": "taglineFr",
          "type": "varchar(512)",
          "primaryKey": false,
          "notNull": false,
          "autoincrement": false
        },
        "taglineJa": {
          "name": "taglineJa",
          "type": "varchar(512)",
          "primaryKey": false,
          "notNull": false,
          "autoincrement": false
        },
        "descriptionEn": {
          "name": "descriptionEn",
          "type": "text",
          "primaryKey": false,
          "notNull": false,
          "autoincrement": false
        },
        "descriptionZh": {
          "name": "descriptionZh",
          "type": "text",
          "primaryKey": false,
          "notNull": false,
          "autoincrement": false
        },
        "descriptionFr": {
          "name": "descriptionFr",
          "type": "text",
          "primaryKey": false,
          "notNull": false,
          "autoincrement": false
        },
        "descriptionJa": {
          "name": "descriptionJa",
          "type": "text",
          "primaryKey": false,
          "notNull": false,
          "autoincrement": false
        },
        "iconUrl": {
          "name": "iconUrl",
          "type": "varchar(512)",
          "primaryKey": false,
          "notNull": false,
          "autoincrement": false
        },
        "themeColor": {
          "name": "themeColor",
          "type": "varchar(16)",
          "primaryKey": false,
          "notNull": false,
          "autoincrement": false
        },
        "isVisible": {
          "name": "isVisible",
          "type": "enum('visible','hidden')",
          "primaryKey": false,
          "notNull": true,
          "autoincrement": false,
          "default": "'visible'"
        },
        "displayOrder": {
          "name": "displayOrder",
          "type": "int",
          "primaryKey": false,
          "notNull": true,
          "autoincrement": false,
          "default": 0
        },
        "createdAt": {
          "name": "createdAt",
          "type": "timestamp",
          "primaryKey": false,
          "notNull": true,
          "autoincrement": false,
          "default": "(now())"
        },
        "updatedAt": {
          "name": "updatedAt",
          "type": "timestamp",
          "primaryKey": false,
          "notNull": true,
          "autoincrement": false,
          "onUpdate": true,
          "default": "(now())"
        }
      },
      "indexes": {},
      "foreignKeys": {},
      "compositePrimaryKeys": {
        "methodologies_id": {
          "name": "methodologies_id",
          "columns": [
            "id"
          ]
        }
      },
      "uniqueConstraints": {
        "methodologies_slug_unique": {
          "name": "methodologies_slug_unique",
          "columns": [
            "slug"
          ]
        }
      },
      "checkConstraint": {}
    },
    "milestones": {
      "name": "milestones",
      "columns": {
        "id": {
          "name": "id",
          "type": "int",
          "primaryKey": false,
          "notNull": true,
          "autoincrement": true
        },
        "category": {
          "name": "category",
          "type": "varchar(128)",
          "primaryKey": false,
          "notNull": true,
          "autoincrement": false
        },
        "sourceNameEn": {
          "name": "sourceNameEn",
          "type": "varchar(255)",
          "primaryKey": false,
          "notNull": true,
          "autoincrement": false
        },
        "sourceNameZh": {
          "name": "sourceNameZh",
          "type": "varchar(255)",
          "primaryKey": false,
          "notNull": false,
          "autoincrement": false
        },
        "sourceNameFr": {
          "name": "sourceNameFr",
          "type": "varchar(255)",
          "primaryKey": false,
          "notNull": false,
          "autoincrement": false
        },
        "sourceNameJa": {
          "name": "sourceNameJa",
          "type": "varchar(255)",
          "primaryKey": false,
          "notNull": false,
          "autoincrement": false
        },
        "descriptionEn": {
          "name": "descriptionEn",
          "type": "text",
          "primaryKey": false,
          "notNull": false,
          "autoincrement": false
        },
        "descriptionZh": {
          "name": "descriptionZh",
          "type": "text",
          "primaryKey": false,
          "notNull": false,
          "autoincrement": false
        },
        "descriptionFr": {
          "name": "descriptionFr",
          "type": "text",
          "primaryKey": false,
          "notNull": false,
          "autoincrement": false
        },
        "descriptionJa": {
          "name": "descriptionJa",
          "type": "text",
          "primaryKey": false,
          "notNull": false,
          "autoincrement": false
        },
        "publishDate": {
          "name": "publishDate",
          "type": "varchar(32)",
          "primaryKey": false,
          "notNull": false,
          "autoincrement": false
        },
        "sourceType": {
          "name": "sourceType",
          "type": "varchar(128)",
          "primaryKey": false,
          "notNull": false,
          "autoincrement": false
        },
        "url": {
          "name": "url",
          "type": "varchar(1024)",
          "primaryKey": false,
          "notNull": false,
          "autoincrement": false
        },
        "country": {
          "name": "country",
          "type": "varchar(64)",
          "primaryKey": false,
          "notNull": false,
          "autoincrement": false
        },
        "year": {
          "name": "year",
          "type": "int",
          "primaryKey": false,
          "notNull": false,
          "autoincrement": false
        },
        "isVisible": {
          "name": "isVisible",
          "type": "enum('visible','hidden')",
          "primaryKey": false,
          "notNull": true,
          "autoincrement": false,
          "default": "'visible'"
        },
        "displayOrder": {
          "name": "displayOrder",
          "type": "int",
          "primaryKey": false,
          "notNull": true,
          "autoincrement": false,
          "default": 0
        },
        "createdAt": {
          "name": "createdAt",
          "type": "timestamp",
          "primaryKey": false,
          "notNull": true,
          "autoincrement": false,
          "default": "(now())"
        },
        "updatedAt": {
          "name": "updatedAt",
          "type": "timestamp",
          "primaryKey": false,
          "notNull": true,
          "autoincrement": false,
          "onUpdate": true,
          "default": "(now())"
        }
      },
      "indexes": {},
      "foreignKeys": {},
      "compositePrimaryKeys": {
        "milestones_id": {
          "name": "milestones_id",
          "columns": [
            "id"
          ]
        }
      },
      "uniqueConstraints": {},
      "checkConstraint": {}
    },
    "partner_applications": {
      "name": "partner_applications",
      "columns": {
        "id": {
          "name": "id",
          "type": "int",
          "primaryKey": false,
          "notNull": true,
          "autoincrement": true
        },
        "contactName": {
          "name": "contactName",
          "type": "varchar(255)",
          "primaryKey": false,
          "notNull": true,
          "autoincrement": false
        },
        "contactEmail": {
          "name": "contactEmail",
          "type": "varchar(320)",
          "primaryKey": false,
          "notNull": true,
          "autoincrement": false
        },
        "contactPhone": {
          "name": "contactPhone",
          "type": "varchar(64)",
          "primaryKey": false,
          "notNull": false,
          "autoincrement": false
        },
        "organizationName": {
          "name": "organizationName",
          "type": "varchar(255)",
          "primaryKey": false,
          "notNull": true,
          "autoincrement": false
        },
        "organizationType": {
          "name": "organizationType",
          "type": "enum('coach','brand','organization')",
          "primaryKey": false,
          "notNull": true,
          "autoincrement": false
        },
        "description": {
          "name": "description",
          "type": "text",
          "primaryKey": false,
          "notNull": false,
          "autoincrement": false
        },
        "websiteUrl": {
          "name": "websiteUrl",
          "type": "varchar(512)",
          "primaryKey": false,
          "notNull": false,
          "autoincrement": false
        },
        "status": {
          "name": "status",
          "type": "enum('pending','reviewing','approved','rejected')",
          "primaryKey": false,
          "notNull": true,
          "autoincrement": false,
          "default": "'pending'"
        },
        "adminNotes": {
          "name": "adminNotes",
          "type": "text",
          "primaryKey": false,
          "notNull": false,
          "autoincrement": false
        },
        "createdAt": {
          "name": "createdAt",
          "type": "timestamp",
          "primaryKey": false,
          "notNull": true,
          "autoincrement": false,
          "default": "(now())"
        },
        "updatedAt": {
          "name": "updatedAt",
          "type": "timestamp",
          "primaryKey": false,
          "notNull": true,
          "autoincrement": false,
          "onUpdate": true,
          "default": "(now())"
        }
      },
      "indexes": {},
      "foreignKeys": {},
      "compositePrimaryKeys": {
        "partner_applications_id": {
          "name": "partner_applications_id",
          "columns": [
            "id"
          ]
        }
      },
      "uniqueConstraints": {},
      "checkConstraint": {}
    },
    "partners": {
      "name": "partners",
      "columns": {
        "id": {
          "name": "id",
          "type": "int",
          "primaryKey": false,
          "notNull": true,
          "autoincrement": true
        },
        "type": {
          "name": "type",
          "type": "enum('coach','brand','organization')",
          "primaryKey": false,
          "notNull": true,
          "autoincrement": false
        },
        "nameEn": {
          "name": "nameEn",
          "type": "varchar(255)",
          "primaryKey": false,
          "notNull": true,
          "autoincrement": false
        },
        "nameZh": {
          "name": "nameZh",
          "type": "varchar(255)",
          "primaryKey": false,
          "notNull": false,
          "autoincrement": false
        },
        "nameFr": {
          "name": "nameFr",
          "type": "varchar(255)",
          "primaryKey": false,
          "notNull": false,
          "autoincrement": false
        },
        "nameJa": {
          "name": "nameJa",
          "type": "varchar(255)",
          "primaryKey": false,
          "notNull": false,
          "autoincrement": false
        },
        "descriptionEn": {
          "name": "descriptionEn",
          "type": "text",
          "primaryKey": false,
          "notNull": false,
          "autoincrement": false
        },
        "descriptionZh": {
          "name": "descriptionZh",
          "type": "text",
          "primaryKey": false,
          "notNull": false,
          "autoincrement": false
        },
        "descriptionFr": {
          "name": "descriptionFr",
          "type": "text",
          "primaryKey": false,
          "notNull": false,
          "autoincrement": false
        },
        "descriptionJa": {
          "name": "descriptionJa",
          "type": "text",
          "primaryKey": false,
          "notNull": false,
          "autoincrement": false
        },
        "logoUrl": {
          "name": "logoUrl",
          "type": "varchar(512)",
          "primaryKey": false,
          "notNull": false,
          "autoincrement": false
        },
        "websiteUrl": {
          "name": "websiteUrl",
          "type": "varchar(512)",
          "primaryKey": false,
          "notNull": false,
          "autoincrement": false
        },
        "contactEmail": {
          "name": "contactEmail",
          "type": "varchar(320)",
          "primaryKey": false,
          "notNull": false,
          "autoincrement": false
        },
        "isVisible": {
          "name": "isVisible",
          "type": "enum('visible','hidden')",
          "primaryKey": false,
          "notNull": true,
          "autoincrement": false,
          "default": "'visible'"
        },
        "displayOrder": {
          "name": "displayOrder",
          "type": "int",
          "primaryKey": false,
          "notNull": true,
          "autoincrement": false,
          "default": 0
        },
        "metadata": {
          "name": "metadata",
          "type": "json",
          "primaryKey": false,
          "notNull": false,
          "autoincrement": false
        },
        "createdAt": {
          "name": "createdAt",
          "type": "timestamp",
          "primaryKey": false,
          "notNull": true,
          "autoincrement": false,
          "default": "(now())"
        },
        "updatedAt": {
          "name": "updatedAt",
          "type": "timestamp",
          "primaryKey": false,
          "notNull": true,
          "autoincrement": false,
          "onUpdate": true,
          "default": "(now())"
        }
      },
      "indexes": {},
      "foreignKeys": {},
      "compositePrimaryKeys": {
        "partners_id": {
          "name": "partners_id",
          "columns": [
            "id"
          ]
        }
      },
      "uniqueConstraints": {},
      "checkConstraint": {}
    },
    "projects": {
      "name": "projects",
      "columns": {
        "id": {
          "name": "id",
          "type": "int",
          "primaryKey": false,
          "notNull": true,
          "autoincrement": true
        },
        "userId": {
          "name": "userId",
          "type": "int",
          "primaryKey": false,
          "notNull": true,
          "autoincrement": false
        },
        "applicationId": {
          "name": "applicationId",
          "type": "int",
          "primaryKey": false,
          "notNull": true,
          "autoincrement": false
        },
        "title": {
          "name": "title",
          "type": "varchar(255)",
          "primaryKey": false,
          "notNull": true,
          "autoincrement": false
        },
        "titleI18n": {
          "name": "titleI18n",
          "type": "json",
          "primaryKey": false,
          "notNull": false,
          "autoincrement": false
        },
        "description": {
          "name": "description",
          "type": "text",
          "primaryKey": false,
          "notNull": false,
          "autoincrement": false
        },
        "descriptionI18n": {
          "name": "descriptionI18n",
          "type": "json",
          "primaryKey": false,
          "notNull": false,
          "autoincrement": false
        },
        "progress": {
          "name": "progress",
          "type": "int",
          "primaryKey": false,
          "notNull": true,
          "autoincrement": false,
          "default": 0
        },
        "status": {
          "name": "status",
          "type": "enum('active','completed','paused','cancelled')",
          "primaryKey": false,
          "notNull": true,
          "autoincrement": false,
          "default": "'active'"
        },
        "milestones": {
          "name": "milestones",
          "type": "json",
          "primaryKey": false,
          "notNull": false,
          "autoincrement": false
        },
        "createdAt": {
          "name": "createdAt",
          "type": "timestamp",
          "primaryKey": false,
          "notNull": true,
          "autoincrement": false,
          "default": "(now())"
        },
        "updatedAt": {
          "name": "updatedAt",
          "type": "timestamp",
          "primaryKey": false,
          "notNull": true,
          "autoincrement": false,
          "onUpdate": true,
          "default": "(now())"
        }
      },
      "indexes": {},
      "foreignKeys": {},
      "compositePrimaryKeys": {
        "projects_id": {
          "name": "projects_id",
          "columns": [
            "id"
          ]
        }
      },
      "uniqueConstraints": {},
      "checkConstraint": {}
    },
    "translations": {
      "name": "translations",
      "columns": {
        "id": {
          "name": "id",
          "type": "int",
          "primaryKey": false,
          "notNull": true,
          "autoincrement": true
        },
        "key": {
          "name": "key",
          "type": "varchar(128)",
          "primaryKey": false,
          "notNull": true,
          "autoincrement": false
        },
        "category": {
          "name": "category",
          "type": "varchar(64)",
          "primaryKey": false,
          "notNull": false,
          "autoincrement": false
        },
        "en": {
          "name": "en",
          "type": "text",
          "primaryKey": false,
          "notNull": false,
          "autoincrement": false
        },
        "zh": {
          "name": "zh",
          "type": "text",
          "primaryKey": false,
          "notNull": false,
          "autoincrement": false
        },
        "fr": {
          "name": "fr",
          "type": "text",
          "primaryKey": false,
          "notNull": false,
          "autoincrement": false
        },
        "ja": {
          "name": "ja",
          "type": "text",
          "primaryKey": false,
          "notNull": false,
          "autoincrement": false
        },
        "createdAt": {
          "name": "createdAt",
          "type": "timestamp",
          "primaryKey": false,
          "notNull": true,
          "autoincrement": false,
          "default": "(now())"
        },
        "updatedAt": {
          "name": "updatedAt",
          "type": "timestamp",
          "primaryKey": false,
          "notNull": true,
          "autoincrement": false,
          "onUpdate": true,
          "default": "(now())"
        }
      },
      "indexes": {},
      "foreignKeys": {},
      "compositePrimaryKeys": {
        "translations_id": {
          "name": "translations_id",
          "columns": [
            "id"
          ]
        }
      },
      "uniqueConstraints": {
        "translations_key_unique": {
          "name": "translations_key_unique",
          "columns": [
            "key"
          ]
        }
      },
      "checkConstraint": {}
    },
    "users": {
      "name": "users",
      "columns": {
        "id": {
          "name": "id",
          "type": "int",
          "primaryKey": false,
          "notNull": true,
          "autoincrement": true
        },
        "openId": {
          "name": "openId",
          "type": "varchar(64)",
          "primaryKey": false,
          "notNull": true,
          "autoincrement": false
        },
        "name": {
          "name": "name",
          "type": "text",
          "primaryKey": false,
          "notNull": false,
          "autoincrement": false
        },
        "email": {
          "name": "email",
          "type": "varchar(320)",
          "primaryKey": false,
          "notNull": false,
          "autoincrement": false
        },
        "loginMethod": {
          "name": "loginMethod",
          "type": "varchar(64)",
          "primaryKey": false,
          "notNull": false,
          "autoincrement": false
        },
        "role": {
          "name": "role",
          "type": "enum('user','admin')",
          "primaryKey": false,
          "notNull": true,
          "autoincrement": false,
          "default": "'user'"
        },
        "createdAt": {
          "name": "createdAt",
          "type": "timestamp",
          "primaryKey": false,
          "notNull": true,
          "autoincrement": false,
          "default": "(now())"
        },
        "updatedAt": {
          "name": "updatedAt",
          "type": "timestamp",
          "primaryKey": false,
          "notNull": true,
          "autoincrement": false,
          "onUpdate": true,
          "default": "(now())"
        },
        "lastSignedIn": {
          "name": "lastSignedIn",
          "type": "timestamp",
          "primaryKey": false,
          "notNull": true,
          "autoincrement": false,
          "default": "(now())"
        }
      },
      "indexes": {},
      "foreignKeys": {},
      "compositePrimaryKeys": {
        "users_id": {
          "name": "users_id",
          "columns": [
            "id"
          ]
        }
      },
      "uniqueConstraints": {
        "users_openId_unique": {
          "name": "users_openId_unique",
          "columns": [
            "openId"
          ]
        }
      },
      "checkConstraint": {}
    }
  },
  "views": {},
  "_meta": {
    "schemas": {},
    "tables": {},
    "columns": {}
  },
  "internal": {
    "tables": {},
    "indexes": {}
  }
}